{
  "main": {
    "id": "1f38f4a932d2d97c",
    "type": "split",
    "children": [
      {
        "id": "1f41155fcc8206e7",
        "type": "tabs",
        "children": [
          {
            "id": "fbff0a84337c5b9d",
            "type": "leaf",
            "state": {
              "type": "markdown",
              "state": {
                "file": "Theory/Theory Contents.md",
                "mode": "preview",
                "backlinks": false,
                "source": false
              }
            }
          },
          {
            "id": "b41ba645b79dc8f3",
            "type": "leaf",
            "state": {
              "type": "empty",
              "state": {}
            }
          },
          {
            "id": "ede59cfa5979b77e",
            "type": "leaf",
            "state": {
              "type": "markdown",
              "state": {
                "file": "Theory/Big O.md",
                "mode": "preview",
                "backlinks": false,
                "source": false
              }
            }
          },
          {
            "id": "74179f63ad25a607",
            "type": "leaf",
            "state": {
              "type": "markdown",
              "state": {
                "file": "Theory/Types.md",
                "mode": "source",
                "backlinks": false,
                "source": false
              }
            }
          }
        ]
      }
    ],
    "direction": "vertical"
  },
  "left": {
    "id": "83fc1afffb9a7b71",
    "type": "split",
    "children": [
      {
        "id": "b23c023f627054f5",
        "type": "tabs",
        "children": [
          {
            "id": "f56fe916c3f9323c",
            "type": "leaf",
            "state": {
              "type": "file-explorer",
              "state": {
                "sortOrder": "alphabetical"
              }
            }
          },
          {
            "id": "ffdeb4d5a86870dc",
            "type": "leaf",
            "state": {
              "type": "search",
              "state": {
                "query": "",
                "matchingCase": false,
                "explainSearch": false,
                "collapseAll": false,
                "extraContext": false,
                "sortOrder": "alphabetical"
              }
            }
          },
          {
            "id": "2fd59c0ef4e892d0",
            "type": "leaf",
            "state": {
              "type": "bookmarks",
              "state": {}
            }
          }
        ],
        "currentTab": 2
      }
    ],
    "direction": "horizontal",
    "width": 200
  },
  "right": {
    "id": "7d7c383c832ac0de",
    "type": "split",
    "children": [
      {
        "id": "928a529fe2b22def",
        "type": "tabs",
        "children": [
          {
            "id": "7f6b93d4ecbb40ff",
            "type": "leaf",
            "state": {
              "type": "backlink",
              "state": {
                "file": "Theory/Theory Contents.md",
                "collapseAll": false,
                "extraContext": false,
                "sortOrder": "alphabetical",
                "showSearch": false,
                "searchQuery": "",
                "backlinkCollapsed": false,
                "unlinkedCollapsed": true
              }
            }
          },
          {
            "id": "48a57d8fd7f901ef",
            "type": "leaf",
            "state": {
              "type": "outgoing-link",
              "state": {
                "file": "Theory/Theory Contents.md",
                "linksCollapsed": false,
                "unlinkedCollapsed": true
              }
            }
          },
          {
            "id": "6bfd1307cb6eaa83",
            "type": "leaf",
            "state": {
              "type": "tag",
              "state": {
                "sortOrder": "frequency",
                "useHierarchy": true
              }
            }
          },
          {
            "id": "5fb50a04443bc950",
            "type": "leaf",
            "state": {
              "type": "outline",
              "state": {
                "file": "Theory/Theory Contents.md"
              }
            }
          }
        ]
      }
    ],
    "direction": "horizontal",
    "width": 300,
    "collapsed": true
  },
  "left-ribbon": {
    "hiddenItems": {
      "obsidian-excalidraw-plugin:Create new drawing": false,
      "switcher:Open quick switcher": false,
      "graph:Open graph view": false,
      "canvas:Create new canvas": false,
      "daily-notes:Open today's daily note": false,
      "templates:Insert template": false,
      "command-palette:Open command palette": false
    }
  },
  "active": "fbff0a84337c5b9d",
  "lastOpenFiles": [
    "Theory/Visualization.md",
    "Theory/Theory Contents.md",
    "Theory/Iris Dataset.md",
    "Theory/Time Data.md",
    "Theory/Interacting further with DataFrames.md",
    "Theory/Interacting with DataFrames.md",
    "Excalidraw/Drawing 2024-04-08 10.36.34.excalidraw.md",
    "Theory/Pandas Indexer.md",
    "Theory/Pandas DataFrame.md",
    "Theory/Pandas Series.md",
    "Excalidraw/Drawing 2024-04-07 19.44.41.excalidraw.md",
    "Excalidraw",
    "Algorithm/Palindrome.md",
    "Algorithm/Algorithms Home Page.md",
    "Algorithm/Fibonacci.md",
    "Algorithm/Factorial.md",
    "Algorithm/Binary Power.md",
    "Algorithm/Binary Search.md",
    "Theory/NumPy end.md",
    "Theory/uFuncs and Broadcasting.md",
    "Theory/Interacting with ndarray.md",
    "Theory/NumPy Intro.md",
    "Theory/Types.md",
    "Theory/IPython added functionality.md",
    "Theory/Untitled 1.md",
    "Theory/Pasted image 20240404190021.png",
    "Theory/Big O.md",
    "Theory/Untitled.md",
    "Theory",
    "Algorithm/Pasted image 20240331180028.png",
    "Series",
    "Algebra/Pasted image 20240301174908.png",
    "Number Theory/Pasted image 20240229161601.png",
    "Algebra/Pasted image 20240301141259.png",
    "Algebra/Pasted image 20240301141054.png",
    "Number Theory/Excalidraw",
    "Algebra",
    "Number Theory"
  ]
}